pyomo_solver_analyzer/__init__.py
pyomo_solver_analyzer/analyzer.py
pyomo_solver_analyzer/diagnostics.py
pyomo_solver_analyzer/introspection.py
pyomo_solver_analyzer/unfeasibility.py
pyomo_solver_analyzer-0.1.2.dist-info/METADATA
pyomo_solver_analyzer-0.1.2.dist-info/WHEEL
pyomo_solver_analyzer-0.1.2.dist-info/licenses/LICENSE
pyomo_solver_analyzer-0.1.2.dist-info/RECORD
