Metadata-Version: 2.4
Name: pyomo-solver-analyzer
Version: 0.1.2
Summary: Automatic constraint analysis and debugging for Pyomo linear solvers
Project-URL: Repository, https://github.com/jaimeam/Pyomo-Solver-Analyzer
Project-URL: Documentation, https://github.com/jaimeam/Pyomo-Solver-Analyzer/wiki
Project-URL: Bug Tracker, https://github.com/jaimeam/Pyomo-Solver-Analyzer/issues
Author-email: Jaime Adroher <jaime.adroher@gmail.com>
License: MIT
License-File: LICENSE
Keywords: analysis,constraints,debugging,optimization,pyomo,solver
Classifier: Development Status :: 3 - Alpha
Classifier: Intended Audience :: Science/Research
Classifier: License :: OSI Approved :: MIT License
Classifier: Programming Language :: Python :: 3
Classifier: Programming Language :: Python :: 3.8
Classifier: Programming Language :: Python :: 3.9
Classifier: Programming Language :: Python :: 3.10
Classifier: Programming Language :: Python :: 3.11
Classifier: Programming Language :: Python :: 3.12
Classifier: Topic :: Scientific/Engineering :: Mathematics
Requires-Python: >=3.8
Requires-Dist: pyomo>=6.0
Provides-Extra: dev
Requires-Dist: mypy>=1.0; extra == 'dev'
Requires-Dist: pre-commit>=3.0; extra == 'dev'
Requires-Dist: pytest-cov>=4.0; extra == 'dev'
Requires-Dist: pytest>=7.0; extra == 'dev'
Requires-Dist: ruff>=0.1.0; extra == 'dev'
Provides-Extra: test
Requires-Dist: pytest-cov>=4.0; extra == 'test'
Requires-Dist: pytest>=7.0; extra == 'test'
